fallixy-0.18.1.dist-info/DESCRIPTION.rst
fallixy-0.18.1.dist-info/METADATA
fallixy-0.18.1.dist-info/RECORD
fallixy-0.18.1.dist-info/WHEEL
fallixy-0.18.1.dist-info/entry_points.txt
fallixy-0.18.1.dist-info/metadata.json
fallixy-0.18.1.dist-info/top_level.txt
mitmproxy/__init__.py
mitmproxy/addons.py
mitmproxy/cmdline.py
mitmproxy/contentviews.py
mitmproxy/controller.py
mitmproxy/ctx.py
mitmproxy/dump.py
mitmproxy/exceptions.py
mitmproxy/filt.py
mitmproxy/flowfilter.py
mitmproxy/main.py
mitmproxy/options.py
mitmproxy/optmanager.py
mitmproxy/stateobject.py
mitmproxy/utils.py
mitmproxy/builtins/__init__.py
mitmproxy/builtins/anticache.py
mitmproxy/builtins/anticomp.py
mitmproxy/builtins/clientplayback.py
mitmproxy/builtins/dumper.py
mitmproxy/builtins/filestreamer.py
mitmproxy/builtins/replace.py
mitmproxy/builtins/script.py
mitmproxy/builtins/serverplayback.py
mitmproxy/builtins/setheaders.py
mitmproxy/builtins/stickyauth.py
mitmproxy/builtins/stickycookie.py
mitmproxy/builtins/termlog.py
mitmproxy/console/__init__.py
mitmproxy/console/common.py
mitmproxy/console/flowdetailview.py
mitmproxy/console/flowlist.py
mitmproxy/console/flowview.py
mitmproxy/console/grideditor.py
mitmproxy/console/help.py
mitmproxy/console/hk_new_set_of_bugs
mitmproxy/console/master.py
mitmproxy/console/options.py
mitmproxy/console/palettepicker.py
mitmproxy/console/palettes.py
mitmproxy/console/pathedit.py
mitmproxy/console/searchable.py
mitmproxy/console/select.py
mitmproxy/console/signals.py
mitmproxy/console/statusbar.py
mitmproxy/console/tabs.py
mitmproxy/console/window.py
mitmproxy/console/grideditor/__init__.py
mitmproxy/console/grideditor/base.py
mitmproxy/console/grideditor/col_bytes.py
mitmproxy/console/grideditor/col_subgrid.py
mitmproxy/console/grideditor/col_text.py
mitmproxy/console/grideditor/editors.py
mitmproxy/contrib/README
mitmproxy/contrib/__init__.py
mitmproxy/contrib/tnetstring.py
mitmproxy/contrib/tls/__init__.py
mitmproxy/contrib/tls/_constructs.py
mitmproxy/contrib/tls/utils.py
mitmproxy/contrib/wbxml/ASCommandResponse.py
mitmproxy/contrib/wbxml/ASWBXML.py
mitmproxy/contrib/wbxml/ASWBXMLByteQueue.py
mitmproxy/contrib/wbxml/ASWBXMLCodePage.py
