Metadata-Version: 2.0
Name: fallixy
Version: 0.18.1
Summary: (Fallible version with extras)An interactive, MITM HTTP proxy for penetration testers and software developers.
Home-page: http://github.com/mkagenius/mitmproxy
Author: Fallible
Author-email: hello@fallible.co
License: MIT
Platform: UNKNOWN
Classifier: License :: OSI Approved :: MIT License
Classifier: Development Status :: 5 - Production/Stable
Classifier: Environment :: Console
Classifier: Environment :: Console :: Curses
Classifier: Operating System :: MacOS :: MacOS X
Classifier: Operating System :: POSIX
Classifier: Operating System :: Microsoft :: Windows
Classifier: Programming Language :: Python
Classifier: Programming Language :: Python :: 2
Classifier: Programming Language :: Python :: 2.7
Classifier: Programming Language :: Python :: 3
Classifier: Programming Language :: Python :: 3.5
Classifier: Programming Language :: Python :: Implementation :: CPython
Classifier: Programming Language :: Python :: Implementation :: PyPy
Classifier: Topic :: Security
Classifier: Topic :: Internet
Classifier: Topic :: Internet :: WWW/HTTP
Classifier: Topic :: Internet :: Proxy Servers
Classifier: Topic :: Software Development :: Testing
Requires-Dist: Flask (<0.12,>=0.10.1)
Requires-Dist: Pillow (>=3.2,<3.5)
Requires-Dist: backports.ssl-match-hostname (>=3.5.0.1,<3.6)
Requires-Dist: blinker (<1.5,>=1.4)
Requires-Dist: brotlipy (<0.7,>=0.5.1)
Requires-Dist: certifi (>=2015.11.20.1)
Requires-Dist: click (<7.0,>=6.2)
Requires-Dist: configargparse (<0.12,>=0.10)
Requires-Dist: construct (>=2.5.2,<2.6)
Requires-Dist: cryptography (>=1.3,<1.6)
Requires-Dist: cssutils (>=1.0.1,<1.1)
Requires-Dist: h2 (>=2.4.1,<3)
Requires-Dist: html2text (<=2016.9.19,>=2016.1.8)
Requires-Dist: hyperframe (<5,>=4.0.1)
Requires-Dist: jsbeautifier (>=1.6.3,<1.7)
Requires-Dist: lxml (<=3.6.0,>=3.5.0)
Requires-Dist: passlib (>=1.6.5,<1.7)
Requires-Dist: pyOpenSSL (>=16.0,<17.0)
Requires-Dist: pyasn1 (>=0.1.9,<0.2)
Requires-Dist: pyparsing (>=2.1.3,<2.2)
Requires-Dist: pyperclip (>=1.5.22,<1.6)
Requires-Dist: requests (<2.12,>=2.9.1)
Requires-Dist: six (>=1.10,<1.11)
Requires-Dist: tornado (>=4.3,<4.5)
Requires-Dist: urwid (>=1.3.1,<1.4)
Requires-Dist: watchdog (>=0.8.3,<0.9)
Requires-Dist: enum34 (>=1.0.4,<2); python_version == "2.7"
Requires-Dist: ipaddress (<1.1,>=1.0.15); python_version == "2.7"
Requires-Dist: typing (==3.5.2.2); python_version == "2.7"
Requires-Dist: pydivert (>=0.0.7,<0.1); sys_platform == "win32"
Provides-Extra: contentviews
Provides-Extra: dev
Requires-Dist: mock (<2.1,>=2.0); extra == 'dev'
Requires-Dist: pytest (<3.1,>=3); extra == 'dev'
Requires-Dist: pytest-cov (>=2.2.1,<3); extra == 'dev'
Requires-Dist: pytest-faulthandler (>=1.3.0,<2); extra == 'dev'
Requires-Dist: pytest-timeout (>=1.0.0,<2); extra == 'dev'
Requires-Dist: pytest-xdist (>=1.14,<2); extra == 'dev'
Requires-Dist: sphinx (>=1.3.5,<1.5); extra == 'dev'
Requires-Dist: sphinx-autobuild (>=0.5.2,<0.7); extra == 'dev'
Requires-Dist: sphinx-rtd-theme (>=0.1.9,<0.2); extra == 'dev'
Requires-Dist: sphinxcontrib-documentedlist (>=0.4.0,<0.5); extra == 'dev'
Requires-Dist: tox (<3,>=2.3); extra == 'dev'
Provides-Extra: examples
Requires-Dist: beautifulsoup4 (>=4.4.1,<4.6); extra == 'examples'
Requires-Dist: pytz (<=2016.7,>=2015.07.0); extra == 'examples'
